{
  "export": "/Users/ehanson8/Documents/D2l & Coursebuilding Tools /brightspace-blueprint-bundle/examples/sample_export.zip",
  "label": "sample_course",
  "dropbox_folders": [
    {
      "id": "1",
      "name": "Planning Memo",
      "resource_code": "CODE-A1",
      "submission_type": "file",
      "folder_type": "",
      "out_of": "20",
      "grade_item_code": "CODE-G-A1",
      "rubric_ids": [
        "RUB-1"
      ],
      "date_due": "2026-09-20T03:59:59",
      "is_hidden": "",
      "condition_set": "COND-OPEN",
      "instructions_text": "Draft a short planning memo that names the evidence files you inspected. Use one paragraph for the manifest evidence. Use one paragraph for the activity join evidence.",
      "instructions_blocks": [
        {
          "kind": "p",
          "level": 0,
          "runs": [
            {
              "text": "Draft a short planning memo that names the evidence files you inspected.",
              "href": ""
            }
          ]
        },
        {
          "kind": "li",
          "level": 1,
          "runs": [
            {
              "text": "Use one paragraph for the manifest evidence.",
              "href": ""
            }
          ]
        },
        {
          "kind": "li",
          "level": 1,
          "runs": [
            {
              "text": "Use one paragraph for the activity join evidence.",
              "href": ""
            }
          ]
        }
      ],
      "instructions_html": "<p>Draft a short planning memo that names the evidence files you inspected.</p><ul><li>Use one paragraph for the manifest evidence.</li><li>Use one paragraph for the activity join evidence.</li></ul>",
      "images_missing_alt": 0,
      "grade_item_name": "Planning Memo",
      "grade_item_out_of": "20",
      "rubrics_resolved": "RUB-1: Planning Memo Rubric",
      "quicklink_count": 1
    },
    {
      "id": "2",
      "name": "Data Snapshot Worksheet",
      "resource_code": "CODE-A2",
      "submission_type": "file",
      "folder_type": "",
      "out_of": "10",
      "grade_item_code": "CODE-G-A2",
      "rubric_ids": [],
      "date_due": "",
      "is_hidden": "",
      "condition_set": "",
      "instructions_text": "Complete the worksheet using the course activities workbook generated by the bundle.",
      "instructions_blocks": [
        {
          "kind": "p",
          "level": 0,
          "runs": [
            {
              "text": "Complete the worksheet using the course activities workbook generated by the bundle.",
              "href": ""
            }
          ]
        }
      ],
      "instructions_html": "<p>Complete the worksheet using the course activities workbook generated by the bundle.</p>",
      "images_missing_alt": 0,
      "grade_item_name": "Data Snapshot Worksheet",
      "grade_item_out_of": "10",
      "rubrics_resolved": "",
      "quicklink_count": 1
    },
    {
      "id": "3",
      "name": "Reflection Journal",
      "resource_code": "CODE-A3",
      "submission_type": "text",
      "folder_type": "",
      "out_of": "5",
      "grade_item_code": "CODE-G-A3",
      "rubric_ids": [],
      "date_due": "",
      "is_hidden": "",
      "condition_set": "",
      "instructions_text": "Write a short reflection after reviewing Week 2 materials.",
      "instructions_blocks": [
        {
          "kind": "p",
          "level": 0,
          "runs": [
            {
              "text": "Write a short reflection after reviewing Week 2 materials.",
              "href": ""
            }
          ]
        }
      ],
      "instructions_html": "<p>Write a short reflection after reviewing Week 2 materials.</p>",
      "images_missing_alt": 0,
      "grade_item_name": "Reflection Journal",
      "grade_item_out_of": "5",
      "rubrics_resolved": "",
      "quicklink_count": 1
    },
    {
      "id": "4",
      "name": "Unplaced Capstone Draft",
      "resource_code": "CODE-AU",
      "submission_type": "file",
      "folder_type": "",
      "out_of": "15",
      "grade_item_code": "CODE-G-AU",
      "rubric_ids": [],
      "date_due": "",
      "is_hidden": "",
      "condition_set": "",
      "instructions_text": "This assignment is not linked in the manifest and should appear as unplaced.",
      "instructions_blocks": [
        {
          "kind": "p",
          "level": 0,
          "runs": [
            {
              "text": "This assignment is not linked in the manifest and should appear as unplaced.",
              "href": ""
            }
          ]
        }
      ],
      "instructions_html": "<p>This assignment is not linked in the manifest and should appear as unplaced.</p>",
      "images_missing_alt": 0,
      "grade_item_name": "Unplaced Capstone Draft",
      "grade_item_out_of": "15",
      "rubrics_resolved": "",
      "quicklink_count": 0
    }
  ],
  "discussions": [
    {
      "kind": "forum",
      "source_file": "discussion_d2l_1.xml",
      "forum_id": "20",
      "topic_id": "",
      "title": "Course Discussions",
      "resource_code": "CODE-FORUM",
      "score_out_of": "",
      "grade_item_code": "",
      "rubric_ids": [],
      "is_hidden": "False",
      "requires_approval": "",
      "must_post_to_participate": "",
      "condition_set": "",
      "description_text": "",
      "description_html": "",
      "images_missing_alt": 0,
      "grade_item_name": "",
      "grade_item_out_of": "",
      "rubrics_resolved": "",
      "quicklink_count": 0
    },
    {
      "kind": "topic",
      "source_file": "discussion_d2l_1.xml",
      "forum_id": "20",
      "topic_id": "21",
      "title": "Planning Assumptions",
      "resource_code": "CODE-D1",
      "score_out_of": "5",
      "grade_item_code": "CODE-G-D1",
      "rubric_ids": [],
      "is_hidden": "False",
      "requires_approval": "False",
      "must_post_to_participate": "False",
      "condition_set": "",
      "description_text": "Post one assumption you bring into source-traceable course review.",
      "description_blocks": [
        {
          "kind": "p",
          "level": 0,
          "runs": [
            {
              "text": "Post one assumption you bring into source-traceable course review.",
              "href": ""
            }
          ]
        }
      ],
      "description_html": "<p>Post one assumption you bring into source-traceable course review.</p>",
      "images_missing_alt": 0,
      "grade_item_name": "Planning Assumptions",
      "grade_item_out_of": "5",
      "rubrics_resolved": "",
      "quicklink_count": 1
    },
    {
      "kind": "topic",
      "source_file": "discussion_d2l_1.xml",
      "forum_id": "20",
      "topic_id": "22",
      "title": "Peer Reply",
      "resource_code": "CODE-D2",
      "score_out_of": "5",
      "grade_item_code": "CODE-G-D2",
      "rubric_ids": [],
      "is_hidden": "False",
      "requires_approval": "False",
      "must_post_to_participate": "True",
      "condition_set": "",
      "description_text": "Reply to a peer and identify one item that should remain marked for review.",
      "description_blocks": [
        {
          "kind": "p",
          "level": 0,
          "runs": [
            {
              "text": "Reply to a peer and identify one item that should remain marked for review.",
              "href": ""
            }
          ]
        }
      ],
      "description_html": "<p>Reply to a peer and identify one item that should remain marked for review.</p>",
      "images_missing_alt": 0,
      "grade_item_name": "Peer Reply",
      "grade_item_out_of": "5",
      "rubrics_resolved": "",
      "quicklink_count": 1
    },
    {
      "kind": "topic",
      "source_file": "discussion_d2l_1.xml",
      "forum_id": "20",
      "topic_id": "23",
      "title": "Unplaced Help Forum",
      "resource_code": "CODE-DU",
      "score_out_of": "",
      "grade_item_code": "",
      "rubric_ids": [],
      "is_hidden": "False",
      "requires_approval": "False",
      "must_post_to_participate": "False",
      "condition_set": "",
      "description_text": "This discussion topic is not linked in the manifest and should be reported as unplaced.",
      "description_blocks": [
        {
          "kind": "p",
          "level": 0,
          "runs": [
            {
              "text": "This discussion topic is not linked in the manifest and should be reported as unplaced.",
              "href": ""
            }
          ]
        }
      ],
      "description_html": "<p>This discussion topic is not linked in the manifest and should be reported as unplaced.</p>",
      "images_missing_alt": 0,
      "grade_item_name": "",
      "grade_item_out_of": "",
      "rubrics_resolved": "",
      "quicklink_count": 0
    }
  ],
  "checklists": [
    {
      "id": "30",
      "name": "Week 1 Checklist",
      "resource_code": "CODE-CL1",
      "display_in_new_window": "False",
      "blocks": [
        {
          "kind": "label",
          "level": 0,
          "runs": [
            {
              "text": "Review outputs:",
              "href": ""
            }
          ]
        },
        {
          "kind": "li",
          "level": 1,
          "runs": [
            {
              "text": "Open the Markdown blueprint",
              "href": ""
            }
          ]
        },
        {
          "kind": "li",
          "level": 1,
          "runs": [
            {
              "text": "Inspect the DOCX rendering",
              "href": ""
            }
          ]
        },
        {
          "kind": "label",
          "level": 0,
          "runs": [
            {
              "text": "Trace evidence:",
              "href": ""
            }
          ]
        },
        {
          "kind": "li",
          "level": 1,
          "runs": [
            {
              "text": "Compare the manifest probe with the weekly rows",
              "href": ""
            }
          ]
        }
      ],
      "item_count": 3,
      "quicklink_count": 1
    }
  ],
  "quizzes": [
    {
      "source_file": "quiz_d2l_100.xml",
      "id": "",
      "ident": "QUIZ-READY",
      "title": "Readiness Quiz",
      "resource_code": "CODE-Q1",
      "grade_item_code": "CODE-G-Q1",
      "is_active": "yes",
      "attempts_allowed": "1",
      "time_limit_minutes": "20",
      "show_clock": "yes",
      "enforce_time_limit": "yes",
      "mark_calculation_type": "1",
      "date_due": "",
      "section_count": 1,
      "candidate_question_count": 3,
      "draw_count_total": 0,
      "question_type_summary": "",
      "sections": [
        {
          "title": "Evidence Check Pool",
          "draw_count": "",
          "candidate_count": 3,
          "points_per_question": ""
        }
      ],
      "instructions_text": "Complete this short readiness check after reviewing the Week 1 materials. One attempt is allowed. Questions are drawn from a small pool.",
      "instructions_blocks": [
        {
          "kind": "p",
          "level": 0,
          "runs": [
            {
              "text": "Complete this short readiness check after reviewing the Week 1 materials.",
              "href": ""
            }
          ]
        },
        {
          "kind": "li",
          "level": 1,
          "runs": [
            {
              "text": "One attempt is allowed.",
              "href": ""
            }
          ]
        },
        {
          "kind": "li",
          "level": 1,
          "runs": [
            {
              "text": "Questions are drawn from a small pool.",
              "href": ""
            }
          ]
        }
      ],
      "instructions_html": "<p>Complete this short readiness check after reviewing the Week 1 materials.</p><ul><li>One attempt is allowed.</li><li>Questions are drawn from a small pool.</li></ul>",
      "images_missing_alt": 0,
      "quicklink_count": 1,
      "rubric_ids": [],
      "grade_item_name": "Readiness Quiz",
      "grade_item_out_of": "3",
      "rubrics_resolved": ""
    }
  ],
  "grade_items": [
    {
      "id": "10",
      "identifier": "9001",
      "resource_code": "CODE-G-A1",
      "name": "Planning Memo",
      "short_name": "",
      "type_id": "1",
      "is_active": "true",
      "category_id": "",
      "category_name": "",
      "out_of": "20",
      "max_grade": "20",
      "is_bonus": "",
      "exclude_from_final_grade_calc": "",
      "linked_activities": [
        "dropbox_folder: Planning Memo"
      ]
    },
    {
      "id": "11",
      "identifier": "9002",
      "resource_code": "CODE-G-A2",
      "name": "Data Snapshot Worksheet",
      "short_name": "",
      "type_id": "1",
      "is_active": "true",
      "category_id": "",
      "category_name": "",
      "out_of": "10",
      "max_grade": "10",
      "is_bonus": "",
      "exclude_from_final_grade_calc": "",
      "linked_activities": [
        "dropbox_folder: Data Snapshot Worksheet"
      ]
    },
    {
      "id": "12",
      "identifier": "9003",
      "resource_code": "CODE-G-A3",
      "name": "Reflection Journal",
      "short_name": "",
      "type_id": "1",
      "is_active": "true",
      "category_id": "",
      "category_name": "",
      "out_of": "5",
      "max_grade": "5",
      "is_bonus": "",
      "exclude_from_final_grade_calc": "",
      "linked_activities": [
        "dropbox_folder: Reflection Journal"
      ]
    },
    {
      "id": "13",
      "identifier": "9004",
      "resource_code": "CODE-G-Q1",
      "name": "Readiness Quiz",
      "short_name": "",
      "type_id": "1",
      "is_active": "true",
      "category_id": "",
      "category_name": "",
      "out_of": "3",
      "max_grade": "3",
      "is_bonus": "",
      "exclude_from_final_grade_calc": "",
      "linked_activities": [
        "quiz: Readiness Quiz"
      ]
    },
    {
      "id": "14",
      "identifier": "9005",
      "resource_code": "CODE-G-D1",
      "name": "Planning Assumptions",
      "short_name": "",
      "type_id": "1",
      "is_active": "true",
      "category_id": "",
      "category_name": "",
      "out_of": "5",
      "max_grade": "5",
      "is_bonus": "",
      "exclude_from_final_grade_calc": "",
      "linked_activities": [
        "discussion_topic: Planning Assumptions"
      ]
    },
    {
      "id": "15",
      "identifier": "9006",
      "resource_code": "CODE-G-D2",
      "name": "Peer Reply",
      "short_name": "",
      "type_id": "1",
      "is_active": "true",
      "category_id": "",
      "category_name": "",
      "out_of": "5",
      "max_grade": "5",
      "is_bonus": "",
      "exclude_from_final_grade_calc": "",
      "linked_activities": [
        "discussion_topic: Peer Reply"
      ]
    },
    {
      "id": "16",
      "identifier": "9007",
      "resource_code": "CODE-G-AU",
      "name": "Unplaced Capstone Draft",
      "short_name": "",
      "type_id": "1",
      "is_active": "true",
      "category_id": "",
      "category_name": "",
      "out_of": "15",
      "max_grade": "15",
      "is_bonus": "",
      "exclude_from_final_grade_calc": "",
      "linked_activities": [
        "dropbox_folder: Unplaced Capstone Draft"
      ]
    },
    {
      "id": "17",
      "identifier": "9008",
      "resource_code": "CODE-G-ORPHAN",
      "name": "Standalone Participation",
      "short_name": "",
      "type_id": "1",
      "is_active": "true",
      "category_id": "",
      "category_name": "",
      "out_of": "10",
      "max_grade": "10",
      "is_bonus": "",
      "exclude_from_final_grade_calc": "",
      "linked_activities": []
    }
  ],
  "joins": [
    {
      "source_kind": "dropbox_folder",
      "source_name": "Planning Memo",
      "source_code": "CODE-A1",
      "join_type": "grade_item",
      "target": "CODE-G-A1",
      "resolved": "yes"
    },
    {
      "source_kind": "dropbox_folder",
      "source_name": "Planning Memo",
      "source_code": "CODE-A1",
      "join_type": "rubric",
      "target": "RUB-1",
      "resolved": "yes"
    },
    {
      "source_kind": "dropbox_folder",
      "source_name": "Planning Memo",
      "source_code": "CODE-A1",
      "join_type": "condition_set",
      "target": "COND-OPEN",
      "resolved": "yes"
    },
    {
      "source_kind": "dropbox_folder",
      "source_name": "Planning Memo",
      "source_code": "CODE-A1",
      "join_type": "manifest_quicklink",
      "target": "1 link(s)",
      "resolved": "yes"
    },
    {
      "source_kind": "dropbox_folder",
      "source_name": "Data Snapshot Worksheet",
      "source_code": "CODE-A2",
      "join_type": "grade_item",
      "target": "CODE-G-A2",
      "resolved": "yes"
    },
    {
      "source_kind": "dropbox_folder",
      "source_name": "Data Snapshot Worksheet",
      "source_code": "CODE-A2",
      "join_type": "manifest_quicklink",
      "target": "1 link(s)",
      "resolved": "yes"
    },
    {
      "source_kind": "dropbox_folder",
      "source_name": "Reflection Journal",
      "source_code": "CODE-A3",
      "join_type": "grade_item",
      "target": "CODE-G-A3",
      "resolved": "yes"
    },
    {
      "source_kind": "dropbox_folder",
      "source_name": "Reflection Journal",
      "source_code": "CODE-A3",
      "join_type": "manifest_quicklink",
      "target": "1 link(s)",
      "resolved": "yes"
    },
    {
      "source_kind": "dropbox_folder",
      "source_name": "Unplaced Capstone Draft",
      "source_code": "CODE-AU",
      "join_type": "grade_item",
      "target": "CODE-G-AU",
      "resolved": "yes"
    },
    {
      "source_kind": "dropbox_folder",
      "source_name": "Unplaced Capstone Draft",
      "source_code": "CODE-AU",
      "join_type": "manifest_quicklink",
      "target": "0 link(s)",
      "resolved": "none"
    },
    {
      "source_kind": "discussion_topic",
      "source_name": "Planning Assumptions",
      "source_code": "CODE-D1",
      "join_type": "grade_item",
      "target": "CODE-G-D1",
      "resolved": "yes"
    },
    {
      "source_kind": "discussion_topic",
      "source_name": "Planning Assumptions",
      "source_code": "CODE-D1",
      "join_type": "manifest_quicklink",
      "target": "1 link(s)",
      "resolved": "yes"
    },
    {
      "source_kind": "discussion_topic",
      "source_name": "Peer Reply",
      "source_code": "CODE-D2",
      "join_type": "grade_item",
      "target": "CODE-G-D2",
      "resolved": "yes"
    },
    {
      "source_kind": "discussion_topic",
      "source_name": "Peer Reply",
      "source_code": "CODE-D2",
      "join_type": "manifest_quicklink",
      "target": "1 link(s)",
      "resolved": "yes"
    },
    {
      "source_kind": "discussion_topic",
      "source_name": "Unplaced Help Forum",
      "source_code": "CODE-DU",
      "join_type": "manifest_quicklink",
      "target": "0 link(s)",
      "resolved": "none"
    },
    {
      "source_kind": "checklist",
      "source_name": "Week 1 Checklist",
      "source_code": "CODE-CL1",
      "join_type": "manifest_quicklink",
      "target": "1 link(s)",
      "resolved": "yes"
    },
    {
      "source_kind": "quiz",
      "source_name": "Readiness Quiz",
      "source_code": "CODE-Q1",
      "join_type": "grade_item",
      "target": "CODE-G-Q1",
      "resolved": "yes"
    },
    {
      "source_kind": "quiz",
      "source_name": "Readiness Quiz",
      "source_code": "CODE-Q1",
      "join_type": "manifest_quicklink",
      "target": "1 link(s)",
      "resolved": "yes"
    },
    {
      "source_kind": "grade_item",
      "source_name": "Standalone Participation",
      "source_code": "CODE-G-ORPHAN",
      "join_type": "linked_activity",
      "target": "(none found in dropbox/discussions/quizzes)",
      "resolved": "none"
    }
  ],
  "diagnostics": []
}
